lvim/broker.py
lvim/cli.py
lvim/completer.py
lvim/context.py
lvim/defaults.py
lvim/magics.py
lvim/notifications.py
lvim/nvim.py
lvim/pydefaults.py
lvim/pyrepl.py
lvim/repl.py
lvim/session.py
lvim/utils.py
lvim-0.0.4.dist-info/METADATA
lvim-0.0.4.dist-info/WHEEL
lvim-0.0.4.dist-info/entry_points.txt
lvim-0.0.4.dist-info/licenses/LICENSE
lvim-0.0.4.dist-info/RECORD
