Metadata-Version: 2.4
Name: lvim
Version: 0.0.4
Summary: a remote control interpreter for neovim
Project-URL: Repository, https://github.com/adammillerio/lvim
Author-email: Adam Miller <miller@adammiller.io>
License: MIT License
License-File: LICENSE
Classifier: Development Status :: 3 - Alpha
Classifier: Intended Audience :: End Users/Desktop
Classifier: License :: OSI Approved :: MIT License
Classifier: Programming Language :: Python :: 3
Classifier: Programming Language :: Python :: 3 :: Only
Classifier: Programming Language :: Python :: 3.10
Classifier: Programming Language :: Python :: 3.11
Classifier: Programming Language :: Python :: 3.12
Requires-Python: >=3.12
Requires-Dist: click>=8.2.1
Requires-Dist: invoke>=2.2.0
Requires-Dist: platformdirs>=4.3.8
Requires-Dist: prompt-toolkit>=3.0.51
Requires-Dist: pygments>=2.19.1
Requires-Dist: pynvim>=0.5.2
Provides-Extra: dev
Requires-Dist: pyre-check>=0.9.23; extra == 'dev'
Requires-Dist: ruff>=0.11.11; extra == 'dev'
Provides-Extra: ipy
Requires-Dist: ipython>=9.3.0; extra == 'ipy'
Requires-Dist: ptpython>=3.0.30; extra == 'ipy'
Provides-Extra: py
Requires-Dist: ptpython>=3.0.30; extra == 'py'
